higgsfield/__init__.py
higgsfield/checkpoint/__init__.py
higgsfield/checkpoint/fsdp_checkpoint.py
higgsfield/checkpoint/fsdp_utils.py
higgsfield/dataset/__init__.py
higgsfield/dataset/dataset.py
higgsfield/dataset/openai.py
higgsfield/experiment.py
higgsfield/internal/__init__.py
higgsfield/internal/cfg.py
higgsfield/internal/ci/cli.py
higgsfield/internal/ci/setup.py
higgsfield/internal/cli.py
higgsfield/internal/experiment/ast_parser.py
higgsfield/internal/experiment/builder.py
higgsfield/internal/experiment/decorator.py
higgsfield/internal/experiment/params.py
higgsfield/internal/init.py
higgsfield/internal/launch.py
higgsfield/internal/main.py
higgsfield/internal/util.py
higgsfield/llama/__init__.py
higgsfield/llama/llama.py
higgsfield/llama/llama_utils.py
higgsfield/loaders/__init__.py
higgsfield/loaders/llama_loader.py
higgsfield/path.py
higgsfield/rl/README.md
higgsfield/rl/rl_adventure_2/1.actor-critic.ipynb
higgsfield/rl/rl_adventure_2/2.gae.ipynb
higgsfield/rl/rl_adventure_2/3.ppo.ipynb
higgsfield/rl/rl_adventure_2/4.acer.ipynb
higgsfield/rl/rl_adventure_2/5.ddpg.ipynb
higgsfield/rl/rl_adventure_2/6.td3.ipynb
higgsfield/rl/rl_adventure_2/7.soft actor-critic.ipynb
higgsfield/rl/rl_adventure_2/8.gail.ipynb
higgsfield/rl/rl_adventure_2/9.her.ipynb
higgsfield/rl/rl_adventure_2/README.md
higgsfield/rl/rl_adventure_2/common/__init__.py
higgsfield/rl/rl_adventure_2/common/multiprocessing_env.py
higgsfield/static/project/.gitignore
higgsfield/static/project/Dockerfile
higgsfield/static/project/env
higgsfield/static/project/requirements.txt
higgsfield/static/project/src/alpaca_bf16.py
higgsfield/static/project/src/alpaca_fp16.py
higgsfield/static/project/src/dataset.py
higgsfield/static/templates/README_md.j2
higgsfield/static/templates/config_py.j2
higgsfield/static/templates/deploy_action.j2
higgsfield/static/templates/experiment_action.j2
higgsfield/static/templates/kill_action.j2
higgsfield/training/__init__.py
higgsfield/training/grads.py
higgsfield-0.0.3.dist-info/LICENSE
higgsfield-0.0.3.dist-info/METADATA
higgsfield-0.0.3.dist-info/WHEEL
higgsfield-0.0.3.dist-info/entry_points.txt
higgsfield-0.0.3.dist-info/RECORD
