Metadata-Version: 2.1
Name: higgsfield
Version: 0.0.3
Summary: 
License: Apache-2.0
Author: Yerzat Dulat
Author-email: yerzat@higgsfield.ai
Requires-Python: >=3.8.13,<4.0.0
Classifier: License :: OSI Approved :: Apache Software License
Classifier: Programming Language :: Python :: 3
Classifier: Programming Language :: Python :: 3.9
Classifier: Programming Language :: Python :: 3.10
Classifier: Programming Language :: Python :: 3.11
Requires-Dist: asyncer (>=0.0.2,<0.0.3)
Requires-Dist: asyncssh[bcrypt,fido2,libnacl,pyopenssl] (>=2.14.0,<3.0.0)
Requires-Dist: bcrypt (>=4.0.1,<5.0.0)
Requires-Dist: click (>=8.1.7,<9.0.0)
Requires-Dist: cryptography (>=41.0.4,<42.0.0)
Requires-Dist: fabric (>=3.2.2,<4.0.0)
Requires-Dist: fido2 (>=1.1.2,<2.0.0)
Requires-Dist: jinja2 (>=3.1.2,<4.0.0)
Requires-Dist: libsodium (>=2.6.1,<3.0.0)
Requires-Dist: paramiko (>=3.3.1,<4.0.0)
Requires-Dist: pyopenssl (>=23.2.0,<24.0.0)
Requires-Dist: python-dotenv (>=1.0.0,<2.0.0)
Requires-Dist: pyyaml (>=6.0.1,<7.0.0)
Requires-Dist: unidecode (>=1.3.7,<2.0.0)
